{
  "file_id": "GRAMMAR-CONFUSING-EXPRESSIONS-012",
  "title": "혼동하기 쉬운 표현",
  "description": "형태가 유사하거나 의미가 비슷해 혼동하기 쉬운 표현들의 정확한 사용법을 익혀야 합니다.",
  "category_path": ["작성원칙", "문법규칙", "혼동표현"],
  "tags": ["문법", "어휘", "혼동", "유사어", "구분", "용례", "정확한표현"],
  "rules": [
    {
      "rule_id": "GRAMMAR-CONFUSING-EXPRESSIONS-012-01",
      "title": "운영과 운용",
      "content": "단체나 조직은 '운영'하고, 자본이나 자원은 '운용'합니다.",
      "explanation": "의미와 용법이 다르므로 구분해서 사용해야 합니다.",
      "examples": [
        {
          "incorrect": "기재부는 국책사업들도 팀제로 운용하기로 했다.",
          "correct": "기재부는 국책사업들도 팀제로 운영하기로 했다.",
          "description": "단체나 조직을 움직이게 하거나 경영함"
        },
        {
          "incorrect": "특정금전신탁은 회사채나 기업어음으로 운영한다.",
          "correct": "특정금전신탁은 회사채나 기업어음으로 운용한다.",
          "description": "자본, 자금 등을 사용함"
        }
      ],
      "priority": 2,
      "tags": []
    },
    {
      "rule_id": "GRAMMAR-CONFUSING-EXPRESSIONS-012-02",
      "title": "바래다와 바라다",
      "content": "'바래다'는 색이 없어지거나 배웅하는 경우, '바라다'는 희망하는 경우에 사용합니다.",
      "explanation": "의미와 용법이 다르므로 구분해서 사용해야 합니다.",
      "examples": [
        {
          "incorrect": "감사원이 철저히 조사해주기를 바래다고 밝혔다.",
          "correct": "감사원이 철저히 조사해주기를 바란다고 밝혔다.",
          "description": "희망하다, 기대하다"
        },
        {
          "incorrect": "나는 역까지 삼촌을 바라다드렸다.",
          "correct": "나는 역까지 삼촌을 바래다드렸다.",
          "description": "길을 떠나거나 되돌아가는 사람을 배웅하다"
        }
      ],
      "priority": 2,
      "tags": []
    },
    {
      "rule_id": "GRAMMAR-CONFUSING-EXPRESSIONS-012-03",
      "title": "좇다와 쫓다",
      "content": "공간 이동이 없는 경우 '좇다', 실제 공간 이동이 있는 경우 '쫓다'를 사용합니다.",
      "explanation": "의미와 용법이 다르므로 구분해서 사용해야 합니다.",
      "examples": [
        {
          "incorrect": "스승의 의견을 쫓다.",
          "correct": "스승의 의견을 좇다.",
          "description": "공간의 이동이 없을 경우"
        },
        {
          "incorrect": "후발대가 선발대를 좇아가다.",
          "correct": "후발대가 선발대를 쫓아가다.",
          "description": "실제적인 공간의 이동이 있을 경우"
        }
      ],
      "priority": 2,
      "tags": []
    },
    {
      "rule_id": "GRAMMAR-CONFUSING-EXPRESSIONS-012-04",
      "title": "(으)로써와 (으)로서",
      "content": "수단을 나타낼 때는 '(으)로써', 자격을 나타낼 때는 '(으)로서'를 사용합니다.",
      "explanation": "의미와 용법이 다르므로 구분해서 사용해야 합니다.",
      "examples": [
        {
          "incorrect": "대화로서 갈등을 풀 수 있을지 여부가 관건이다.",
          "correct": "대화로써 갈등을 풀 수 있을지 여부가 관건이다.",
          "description": "수단"
        },
        {
          "incorrect": "기관장으로써 부족함이 많다.",
          "correct": "기관장으로서 부족함이 많다.",
          "description": "자격"
        }
      ],
      "priority": 2,
      "tags": []
    },
    {
      "rule_id": "GRAMMAR-CONFUSING-EXPRESSIONS-012-05",
      "title": "에와 에게",
      "content": "무생물에는 '에', 생물(주로 사람)에는 '에게'를 사용합니다.",
      "explanation": "의미와 용법이 다르므로 구분해서 사용해야 합니다.",
      "examples": [
        {
          "incorrect": "이 법은 직원 20인 미만인 기업에게 적용된다.",
          "correct": "이 법은 직원 20인 미만인 기업에 적용된다.",
          "description": "무생물 주어에 사용"
        },
        {
          "incorrect": "이 서비스는 개인에는 무제한 제공된다.",
          "correct": "이 서비스는 개인에게는 무제한 제공된다.",
          "description": "생물 주어에 사용"
        }
      ],
      "priority": 2,
      "tags": []
    }
  ]
}
